setup.py
celery_schedulers/__init__.py
celery_schedulers/mongo_scheduler.py
celery_schedulers/redis_scheduler.py
celery_schedulers.egg-info/PKG-INFO
celery_schedulers.egg-info/SOURCES.txt
celery_schedulers.egg-info/dependency_links.txt
celery_schedulers.egg-info/requires.txt
celery_schedulers.egg-info/top_level.txt