Metadata-Version: 1.1
Name: celery-schedulers
Version: 0.0.4
Summary: Celery scheduler backends for Redis and MongoDB
Home-page: http://bits.btubbs.com/celery-schedulers
Author: Brent Tubbs
Author-email: brent.tubbs@gmail.com
License: UNKNOWN
Platform: UNKNOWN
Classifier: Development Status :: 4 - Beta
Classifier: Intended Audience :: Developers
Classifier: License :: OSI Approved :: BSD License
Classifier: Operating System :: OS Independent
Classifier: Programming Language :: Python
Classifier: Programming Language :: Python :: 2
Classifier: Programming Language :: Python :: 2.7
Classifier: Programming Language :: Python :: 3
